<?xml version="1.0"?>
<page xmlns:xsi="http://www.w3.org/2001/XMLSchema-instance" xsi:noNamespaceSchemaLocation="urn:magento:framework:View/Layout/etc/page_configuration.xsd">
	<body>
		<container name="checkout.cart.coupon">
			<block class="Reward\Point\Block\Frontend\Checkout\EarningRules" name="reward.point.checkout.eaerningrules" template="Reward_Point::displayEarning.phtml" cacheable="false"/>
		</container>
		<referenceContainer name="checkout.cart.methods">
			<block class="Reward\Point\Block\Frontend\Checkout\ExchangeRules" name="reward.point.checkout.exchangerules" template="Reward_Point::Exchange.phtml" cacheable="false"/>
		</referenceContainer>
	</body>
</page>